great_text/__init__.py
great_text/great.py
great_text-0.2.0.dist-info/LICENSE
great_text-0.2.0.dist-info/WHEEL
great_text-0.2.0.dist-info/METADATA
great_text-0.2.0.dist-info/RECORD
