Metadata-Version: 2.1
Name: great-text
Version: 0.2.0
Summary: Add font and color to your Python text.
Home-page: https://github.com/DeepakDarkiee/great-text.git
License: MIT
Keywords: text
Author: Deepak Patidar
Author-email: info.deepakpatidar@gmail.com
Requires-Python: >=3.6.0
Classifier: License :: OSI Approved :: MIT License
Classifier: Programming Language :: Python :: 3
Classifier: Programming Language :: Python :: 3.6
Classifier: Programming Language :: Python :: 3.7
Classifier: Programming Language :: Python :: 3.8
Classifier: Programming Language :: Python :: 3.9
Requires-Dist: pyfiglet (>=0.8.post1,<0.9)
Requires-Dist: termcolor (>=1.1.0,<2.0.0)
Project-URL: Repository, https://github.com/DeepakDarkiee/great-text.git
